katportalclient/__init__.py
katportalclient/client.py
katportalclient/request.py
katportalclient/test/__init__.py
katportalclient/test/test_client.py
katportalclient-0.2.2.dist-info/LICENSE
katportalclient-0.2.2.dist-info/METADATA
katportalclient-0.2.2.dist-info/WHEEL
katportalclient-0.2.2.dist-info/top_level.txt
katportalclient-0.2.2.dist-info/RECORD
