Metadata-Version: 2.1
Name: katportalclient
Version: 0.2.2
Summary: A client for katportal.
Home-page: https://github.com/ska-sa/katportalclient
Author: MeerKAT CAM Team
Author-email: cam@ska.ac.za
License: UNKNOWN
Keywords: meerkat kat ska
Platform: OS Independent
Classifier: Development Status :: 4 - Beta
Classifier: Intended Audience :: Developers
Classifier: License :: OSI Approved :: BSD License
Classifier: Operating System :: OS Independent
Classifier: Programming Language :: Python
Classifier: Programming Language :: Python :: 2
Classifier: Programming Language :: Python :: 2.7
Classifier: Programming Language :: Python :: 3
Classifier: Programming Language :: Python :: 3.3
Classifier: Programming Language :: Python :: 3.4
Classifier: Programming Language :: Python :: 3.5
Classifier: Programming Language :: Python :: 3.6
Classifier: Programming Language :: Python :: 3.7
Classifier: Topic :: Software Development :: Libraries :: Python Modules
Classifier: Topic :: Scientific/Engineering :: Astronomy
Requires-Python: >=2.7, !=3.0.*, !=3.1.*, !=3.2.*, <4
Requires-Dist: future
Requires-Dist: omnijson (>=0.1.2)
Requires-Dist: ujson (>=2.0.0)
Requires-Dist: futures ; python_version < "3"
Requires-Dist: tornado (<5.0,>=4.0) ; python_version < "3"
Requires-Dist: tornado (<7.0,>=4.0) ; python_version >= "3"
